<?xml version="1.0" encoding="utf-8"?>
<!--TODO: XML schema-->
<vh:VersionHistory xmlns:vh="TODO:" xmlns="http://www.w3.org/1999/xhtml" xmlns:i="http://dzonny.cz/xml/schemas/intellisense"
                   xmlns:xsi="http://www.w3.org/2001/XMLSchema-instance"
                   xsi:schemaLocation="http://dzonny.cz/xml/schemas/intellisense DevelopmentTools/Intellisense/intellisense.xsd">
    <vh:version version="1.5.2">
        <vh:i>
            <i:see cref="T:Tools.InternalT.VersionAttribute"/>, <i:see ctef="T:Tools.InternalT.AuthorAttribute"/> and <i:see ctef="T:Tools.InternalT.FirstVersionAttribute"/> marked as obsoltele. Use XML ocumentation tags instead.
            These atributes were replaced with appropriate XML comments.
        </vh:i>
        <vh:i>Tools.InternalT.FirstVersion renamed to <i:see ctef="T:Tools.InternalT.FirstVersionAttribute"/></vh:i>
        <vh:i><i:see cref="T:Tools.ExtensionsT.DelegateExtensions"/> module: Visubility changed from Private to Public.</vh:i>
        <vh:i>Build state of constants <i:see cref="F:Tools.VisualBasicT.Interaction.Null"/> and <i:see cref="F:Tools.VisualBasicT.Interaction.Nothing"/> changed from Nightly to Release</vh:i>
        <vh:i>Created new assemblies Tools.Windows (for Windows Forms and WPF) and Tools.Metadata (for (image) metadata). Namespaces <i:see cref="N:Tools.DrawingT.DrawingIOt"/> and <i:see cref="N:Tools.DrawingT.MetadataT"/> (<i:see cref="N:Tools.MetadataT"/>) relocated to assembly Tools.Metadata; <i:seee cref="N:Tools.WindowsT"/> relocated to assembly Tools.Windows with exception of <i:see. cref="T:Tools.WindowsT.FormsT.UtilitiesT.CategoryAttributeValues"/>.</vh:i>
        <vh:i>A few methods from <i:see cref="T:Tools.CollectionsT.SpecializedT.CollectionTools"/> relocated to <i:see cref="T:Tools.CollectionsT.SpecializedT.FormsCollectionsExtensions"/>.</vh:i>
        <vh:i>Namespace Tools.DrawingT.MetadataT renamed to <i:see cref="N:Tools.MetadataT"/></vh:i>
        <vh:i>Added namespace <i:see cref="N:Tools.Experimental.DevicesT.JoystickT"/></vh:i>
        <vh:i>Added extension method <i:see cref="M:Tools.CollectionsT.SpecializedT.CollectionTools.Import(System.Windows.Forms.ImageList.ImageCollection,System.Windows.Forms.ImageList.ImageCollection)"/>.</vh:i>
        <vh:i>Added namespace <i:see cref="N:Tools.WindowsT.InteropT"/>.</vh:i>
        <vh:i>Fixed: <i:see cref="M:Tools.TypeTools.CanAutomaticallyCreateInstance(System.Type)"/> always returns null.</vh:i>
        <vh:i>Added namespace <i:see cref="N:Tools.WindowsT.FormsT.VisualStylesT"/>.</vh:i>
        <vh:i><i:see cref="T:Tools.MetadataT.ExifT.URational"/> and <i:see cref="T:Tools.MetadataT.ExifT.SRational"/> now have Parse and TryParse methods, implement <i:see cref="T:System.IFormatable"/> and has <i:see cref="T:System.ComponentModel.TypeConverterAttribute"/>.</vh:i>
        <vh:i>Added several <i:see cref="T:System.ComponentModel.BrowsableAttribute"/>(false) and <i:see cref="System.ComponentMode.TypeConverterAttribute"/>(<i:see cref="System.ComponentModel.ExpandableObjectConverter"/>)  for <i:see cref="Tools.MetadataT.ExifT.Ifd"/>'s properties and derived classes' properties.</vh:i>
        <vh:i><i:see cref="T:Tools.CollectionsT.GenericT.DictionaryWithEvents`2"/> implements <i:see cref="IEnumerable`1"/>[<i:typeparamref name="TValue"/>].</vh:i>
        <vh:i>Fixed: Exif <i:see cref="T:Tools.MetadataT.ExifT.SRational"/> and <i:see cref="T:Tools.MetadataT.ExifT.URrational"/> are incorrectly read from image files (2×16 bits instead of 2×32 bits).</vh:i>
        <vh:i><i:see cref="T:Tools.Metadata.ExifT.ExifWriter"/> made public and Exif saving capability added to <i:see cref="T:Tools.Metadata.ExifT.Exif"/>.</vh:i>
        <vh:i>Added <i:see cref="M:Tools.ReflectionT.ReflectionTools.GetOperators"/> overloaed function.</vh:i>
        <vh:i>Added <i:see cref="M:Tools.TypeTools.DynamiCast(System.Object,System.Type)"/> method</vh:i>
        <vh:i><i:see cref="T:Tools.WindowsT.FormsT.ObjectBrowser"/> now has <i:see cref="P:Tools.WindowsT.FormsT.ObjectBrowser.SelectedItem"/> property</vh:i>
        <vh:i>Fixed: Check box on <i:see cref="T:Tools.WindowsT.FormsT.MessageBox"/> does not autosize.</vh:i>
    </vh:version>
</vh:VersionHistory>
